odoo/addons/commission_oca/README.rst
odoo/addons/commission_oca/__init__.py
odoo/addons/commission_oca/__manifest__.py
odoo/addons/commission_oca/data/menuitem_data.xml
odoo/addons/commission_oca/demo/commission_and_agent_demo.xml
odoo/addons/commission_oca/i18n/commission_oca.pot
odoo/addons/commission_oca/i18n/es.po
odoo/addons/commission_oca/i18n/it.po
odoo/addons/commission_oca/i18n/ja.po
odoo/addons/commission_oca/i18n/pt.po
odoo/addons/commission_oca/i18n/pt_BR.po
odoo/addons/commission_oca/i18n/tr.po
odoo/addons/commission_oca/models/__init__.py
odoo/addons/commission_oca/models/commission.py
odoo/addons/commission_oca/models/commission_mixin.py
odoo/addons/commission_oca/models/commission_settlement.py
odoo/addons/commission_oca/models/product_template.py
odoo/addons/commission_oca/models/res_partner.py
odoo/addons/commission_oca/readme/CONFIGURE.md
odoo/addons/commission_oca/readme/CONTRIBUTORS.md
odoo/addons/commission_oca/readme/DESCRIPTION.md
odoo/addons/commission_oca/readme/ROADMAP.md
odoo/addons/commission_oca/readme/USAGE.md
odoo/addons/commission_oca/reports/commission_settlement_report.xml
odoo/addons/commission_oca/reports/report_settlement_templates.xml
odoo/addons/commission_oca/security/commission_security.xml
odoo/addons/commission_oca/security/ir.model.access.csv
odoo/addons/commission_oca/static/description/icon.png
odoo/addons/commission_oca/static/description/icon.svg
odoo/addons/commission_oca/static/description/index.html
odoo/addons/commission_oca/tests/__init__.py
odoo/addons/commission_oca/tests/test_commission.py
odoo/addons/commission_oca/views/commission_mixin_views.xml
odoo/addons/commission_oca/views/commission_settlement_views.xml
odoo/addons/commission_oca/views/commission_views.xml
odoo/addons/commission_oca/views/product_template_views.xml
odoo/addons/commission_oca/views/res_partner_views.xml
odoo/addons/commission_oca/wizards/__init__.py
odoo/addons/commission_oca/wizards/commission_make_settle.py
odoo_addon_commission_oca-19.0.1.0.0.4.dist-info/METADATA
odoo_addon_commission_oca-19.0.1.0.0.4.dist-info/WHEEL
odoo_addon_commission_oca-19.0.1.0.0.4.dist-info/top_level.txt
odoo_addon_commission_oca-19.0.1.0.0.4.dist-info/RECORD
