Metadata-Version: 2.1
Name: odoo-addon-commission_oca
Version: 19.0.1.0.0.4
Requires-Dist: odoo==19.0.*
Summary: Commissions OCA
Home-page: https://github.com/OCA/commission
License: AGPL-3
Author: Tecnativa, Odoo Community Association (OCA)
Author-email: support@odoo-community.org
Classifier: Programming Language :: Python
Classifier: Framework :: Odoo
Classifier: Framework :: Odoo :: 19.0
Classifier: License :: OSI Approved :: GNU Affero General Public License v3
